asyncio_redis_rate_limit/__init__.py
asyncio_redis_rate_limit/compat.py
asyncio_redis_rate_limit/py.typed
asyncio_redis_rate_limit-1.1.0.dist-info/METADATA
asyncio_redis_rate_limit-1.1.0.dist-info/WHEEL
asyncio_redis_rate_limit-1.1.0.dist-info/licenses/LICENSE
asyncio_redis_rate_limit-1.1.0.dist-info/RECORD
