Metadata-Version: 2.4
Name: asyncio-redis-rate-limit
Version: 1.1.0
Summary: Rate limiter for async functions using Redis as a backend
License: MIT
License-File: LICENSE
Keywords: asyncio,rate-limiter,redis,redis-py,aioredis
Author: Nikita Sobolev
Author-email: mail@sobolevn.me
Requires-Python: >=3.10,<4.0
Classifier: Development Status :: 5 - Production/Stable
Classifier: Intended Audience :: Developers
Classifier: License :: OSI Approved :: MIT License
Classifier: Operating System :: OS Independent
Classifier: Programming Language :: Python :: 3
Classifier: Programming Language :: Python :: 3.10
Classifier: Programming Language :: Python :: 3.11
Classifier: Programming Language :: Python :: 3.12
Classifier: Programming Language :: Python :: 3.13
Classifier: Programming Language :: Python :: 3.14
Classifier: Topic :: Software Development :: Libraries :: Python Modules
Provides-Extra: aioredis
Provides-Extra: dev
Provides-Extra: redis
Requires-Dist: aioredis (>=2.0) ; (python_version < "3.11") and (extra == "aioredis" or extra == "dev")
Requires-Dist: redis (>=4.5,<7) ; extra == "redis" or extra == "dev"
Requires-Dist: typing-extensions (>=3.10)
Project-URL: Funding, https://github.com/sponsors/wemake-services
Project-URL: Repository, https://github.com/wemake-services/asyncio-redis-rate-limit
